django_safe_template_engine/__init__.py
django_safe_template_engine/engine.py
django_safe_template_engine/trusted_filters.py
django_safe_template_engine/trusted_tags.py
django_safe_template_engine/validators.py
django_safe_template_engine-1.4.0.dist-info/METADATA
django_safe_template_engine-1.4.0.dist-info/WHEEL
django_safe_template_engine-1.4.0.dist-info/licenses/LICENSE
django_safe_template_engine-1.4.0.dist-info/RECORD
