Metadata-Version: 2.4
Name: django_safe_template_engine
Version: 1.4.0
Summary: A Django template engine to render untrusted template code
Project-URL: Documentation, https://github.com/ronanboiteau/django_safe_template_engine/blob/main/README.md
Project-URL: Repository, https://github.com/ronanboiteau/django_safe_template_engine.git
Project-URL: Issues, https://github.com/ronanboiteau/django_safe_template_engine/issues
Project-URL: Changelog, https://github.com/ronanboiteau/django_safe_template_engine/blob/main/CHANGELOG.md
Author-email: Ronan Boiteau <ronan@boiteau.eu>
Maintainer-email: Ronan Boiteau <ronan@boiteau.eu>
License: BSD 3-Clause License
License-File: LICENSE
Keywords: django,engine,safe,template
Classifier: Development Status :: 5 - Production/Stable
Classifier: Environment :: Web Environment
Classifier: Framework :: Django
Classifier: Framework :: Django :: 3.0
Classifier: Framework :: Django :: 3.1
Classifier: Framework :: Django :: 3.2
Classifier: Framework :: Django :: 4.0
Classifier: Framework :: Django :: 4.1
Classifier: Framework :: Django :: 4.2
Classifier: Framework :: Django :: 5.0
Classifier: Framework :: Django :: 5.1
Classifier: Framework :: Django :: 5.2
Classifier: Intended Audience :: Developers
Classifier: License :: OSI Approved :: BSD License
Classifier: Operating System :: OS Independent
Classifier: Programming Language :: Python
Classifier: Programming Language :: Python :: 3
Classifier: Programming Language :: Python :: 3.8
Classifier: Programming Language :: Python :: 3.9
Classifier: Programming Language :: Python :: 3.10
Classifier: Programming Language :: Python :: 3.11
Classifier: Programming Language :: Python :: 3.12
Requires-Python: >=3.8
Requires-Dist: django<6,>=3.0
